MANIFEST.in
setup.py
bin/create_bootstra386_project
django_bootstra386view_app/__init__.py
django_bootstra386view_app/models.py
django_bootstra386view_app/bootstra.386/css/bootstrap-responsive.css
django_bootstra386view_app/bootstra.386/css/bootstrap.css
django_bootstra386view_app/bootstra.386/css/docs.css
django_bootstra386view_app/bootstra.386/css/sample.css
django_bootstra386view_app/bootstra.386/css/fonts/Fixedsys500c.eot
django_bootstra386view_app/bootstra.386/css/fonts/Fixedsys500c.otf
django_bootstra386view_app/bootstra.386/css/fonts/Fixedsys500c.svg
django_bootstra386view_app/bootstra.386/css/fonts/Fixedsys500c.ttf
django_bootstra386view_app/bootstra.386/css/fonts/Fixedsys500c.woff
django_bootstra386view_app/bootstra.386/img/8x5overlay.png
django_bootstra386view_app/bootstra.386/img/bootstrap-docs-readme.png
django_bootstra386view_app/bootstra.386/img/bootstrap-mdo-sfmoma-01.jpg
django_bootstra386view_app/bootstra.386/img/bootstrap-mdo-sfmoma-02.jpg
django_bootstra386view_app/bootstra.386/img/bootstrap-mdo-sfmoma-03.jpg
django_bootstra386view_app/bootstra.386/img/bs-docs-bootstrap-features.png
django_bootstra386view_app/bootstra.386/img/bs-docs-masthead-pattern.png
django_bootstra386view_app/bootstra.386/img/bs-docs-responsive-illustrations.png
django_bootstra386view_app/bootstra.386/img/bs-docs-twitter-github.png
django_bootstra386view_app/bootstra.386/img/dos-grid.png
django_bootstra386view_app/bootstra.386/img/glyphicons-halflings-white.png
django_bootstra386view_app/bootstra.386/img/glyphicons-halflings.png
django_bootstra386view_app/bootstra.386/img/grid-baseline-20px.png
django_bootstra386view_app/bootstra.386/img/less-logo-large.png
django_bootstra386view_app/bootstra.386/img/responsive-illustrations.png
django_bootstra386view_app/bootstra.386/img/example-sites/8020select.png
django_bootstra386view_app/bootstra.386/img/example-sites/adoptahydrant.png
django_bootstra386view_app/bootstra.386/img/example-sites/breakingnews.png
django_classview_bootstra386.egg-info/PKG-INFO
django_classview_bootstra386.egg-info/SOURCES.txt
django_classview_bootstra386.egg-info/dependency_links.txt
django_classview_bootstra386.egg-info/requires.txt
django_classview_bootstra386.egg-info/top_level.txt