Metadata-Version: 1.1
Name: django-classview-bootstra386
Version: 0.0.4
Summary: Django-Bootstra.386 generic template with class views
Home-page: http://bossiernesto.github.io/django-bootstra.386-classview/
Author: Ernesto Bossi
Author-email: bossi.ernestog@gmail.com
License: BSD-3
Platform: UNKNOWN
Classifier: Development Status :: 3 - Alpha
Classifier: Framework :: Django
Classifier: Operating System :: OS Independent
Classifier: Topic :: Software Development
Classifier: Programming Language :: Python :: 2.7
